jupyterlab_hai_platform_ext/__init__.py
jupyterlab_hai_platform_ext/_version.py
jupyterlab_hai_platform_ext/handlers.py
jupyterlab_hai_platform_ext/utils.py
jupyterlab_hai_platform_ext/labextension/package.json
jupyterlab_hai_platform_ext/labextension/schemas/jupyterlab_hai_platform_ext/config.json
jupyterlab_hai_platform_ext/labextension/schemas/jupyterlab_hai_platform_ext/package.json.orig
jupyterlab_hai_platform_ext/labextension/schemas/jupyterlab_hai_platform_ext/settings.json
jupyterlab_hai_platform_ext/labextension/static/00ab2c2179d2517e6cd10d68b1ce0f6d6df55d6229eacd85443c85d5cc7efde7.ttf
jupyterlab_hai_platform_ext/labextension/static/106.4c992b341b8de000955d.js
jupyterlab_hai_platform_ext/labextension/static/106.4c992b341b8de000955d.js.map
jupyterlab_hai_platform_ext/labextension/static/129.94881e42fc202e8a9c76.js
jupyterlab_hai_platform_ext/labextension/static/129.94881e42fc202e8a9c76.js.map
jupyterlab_hai_platform_ext/labextension/static/14b1c2781079b8bbd42936bd537c192ff27c4030a56c3c42fcefa07389dd40c9.woff
jupyterlab_hai_platform_ext/labextension/static/155.c7c5fc37ad96f2f92e3c.js
jupyterlab_hai_platform_ext/labextension/static/155.c7c5fc37ad96f2f92e3c.js.map
jupyterlab_hai_platform_ext/labextension/static/184.94994b6882009a770a52.js
jupyterlab_hai_platform_ext/labextension/static/184.94994b6882009a770a52.js.LICENSE.txt
jupyterlab_hai_platform_ext/labextension/static/184.94994b6882009a770a52.js.map
jupyterlab_hai_platform_ext/labextension/static/265861bc2a600df7da89e22c6aa3df5cf975477886616641c3a6226c4c41d253.woff2
jupyterlab_hai_platform_ext/labextension/static/286.a1f98424a62523442c5e.js
jupyterlab_hai_platform_ext/labextension/static/286.a1f98424a62523442c5e.js.map
jupyterlab_hai_platform_ext/labextension/static/287.f00ff344e509f49b11a1.js
jupyterlab_hai_platform_ext/labextension/static/287.f00ff344e509f49b11a1.js.map
jupyterlab_hai_platform_ext/labextension/static/392.367692c0bd70e16bb467.js
jupyterlab_hai_platform_ext-7.15.1.dist-info/LICENSE
jupyterlab_hai_platform_ext-7.15.1.dist-info/METADATA
jupyterlab_hai_platform_ext-7.15.1.dist-info/WHEEL
jupyterlab_hai_platform_ext-7.15.1.dist-info/top_level.txt
jupyterlab_hai_platform_ext-7.15.1.dist-info/RECORD
