Metadata-Version: 2.1
Name: jupyterlab-hai-platform-ext
Version: 7.15.1
Summary: A JupyterLab extension to use HAI Platform service
Home-page: https://github.com/my_name/myextension
Author: Highflyer AiLab
License: GPLv3
Keywords: Jupyter,JupyterLab,JupyterLab3
Platform: Linux
Platform: Mac OS X
Platform: Windows
Classifier: License :: OSI Approved :: GNU General Public License v3 (GPLv3)
Classifier: Programming Language :: Python
Classifier: Programming Language :: Python :: 3
Classifier: Programming Language :: Python :: 3.6
Classifier: Programming Language :: Python :: 3.7
Classifier: Programming Language :: Python :: 3.8
Classifier: Framework :: Jupyter
Requires-Python: >=3.6
License-File: LICENSE
Requires-Dist: jupyterlab (~=3.0)
